cachelock.py
cachelock-0.0.3.dist-info/DESCRIPTION.rst
cachelock-0.0.3.dist-info/METADATA
cachelock-0.0.3.dist-info/RECORD
cachelock-0.0.3.dist-info/WHEEL
cachelock-0.0.3.dist-info/metadata.json
cachelock-0.0.3.dist-info/top_level.txt
