Metadata-Version: 2.0
Name: cachelock
Version: 0.0.3
Summary: A simple look that uses the cache as acquirer
Home-page: https://github.com/douglasfarinelli/python-cachelock
Author: Douglas Farinelli
Author-email: douglas.farinelli@gmail.com
License: MIT
Keywords: lock cache once celery tasks single-execution
Platform: any
Classifier: Framework :: Django
Classifier: Intended Audience :: Developers
Classifier: License :: OSI Approved :: MIT License
Classifier: Operating System :: OS Independent
Classifier: Programming Language :: Python :: 3
Classifier: Programming Language :: Python :: 3.6
Requires-Python: >=3.6
